email_widget/__init__.py
email_widget/email.py
email_widget/email_sender.py
email_widget/core/__init__.py
email_widget/core/base.py
email_widget/core/cache.py
email_widget/core/config.py
email_widget/core/enums.py
email_widget/core/logger.py
email_widget/core/template_engine.py
email_widget/core/validators.py
email_widget/utils/__init__.py
email_widget/utils/image_utils.py
email_widget/utils/optional_deps.py
email_widget/widgets/__init__.py
email_widget/widgets/alert_widget.py
email_widget/widgets/button_widget.py
email_widget/widgets/card_widget.py
email_widget/widgets/chart_widget.py
email_widget/widgets/checklist_widget.py
email_widget/widgets/circular_progress_widget.py
email_widget/widgets/column_widget.py
email_widget/widgets/image_widget.py
email_widget/widgets/log_widget.py
email_widget/widgets/metric_widget.py
email_widget/widgets/progress_widget.py
email_widget/widgets/quote_widget.py
email_widget/widgets/separator_widget.py
email_widget/widgets/status_widget.py
email_widget/widgets/table_widget.py
email_widget/widgets/text_widget.py
email_widget/widgets/timeline_widget.py
emailwidget-0.23.1.dist-info/METADATA
emailwidget-0.23.1.dist-info/WHEEL
emailwidget-0.23.1.dist-info/licenses/LICENSE
emailwidget-0.23.1.dist-info/RECORD
