Metadata-Version: 2.4
Name: EmailWidget
Version: 0.23.1
Summary: 🚀 A modern and user-friendly Python email component library that enables you to easily create beautiful HTML email reports
Project-URL: Homepage, https://github.com/271374667/EmailWidget
Project-URL: Source Code, https://github.com/271374667/EmailWidget
Author-email: PythonImporter <271374667@qq.com>
License-File: LICENSE
Requires-Python: >=3.10
Requires-Dist: jinja2>=3.1.6
Provides-Extra: dev
Requires-Dist: bandit>=1.7.5; extra == 'dev'
Requires-Dist: isort>=5.12.0; extra == 'dev'
Requires-Dist: mypy>=1.7.1; extra == 'dev'
Requires-Dist: notebook>=7.4.4; extra == 'dev'
Requires-Dist: safety>=2.3.0; extra == 'dev'
Provides-Extra: lint
Requires-Dist: bandit>=1.7.5; extra == 'lint'
Requires-Dist: isort>=5.12.0; extra == 'lint'
Requires-Dist: mypy>=1.7.1; extra == 'lint'
Requires-Dist: ruff>=0.1.7; extra == 'lint'
Requires-Dist: safety>=2.3.0; extra == 'lint'
Provides-Extra: test
Requires-Dist: pytest-cov>=4.0.0; extra == 'test'
Requires-Dist: pytest-mock>=3.12.0; extra == 'test'
Requires-Dist: pytest>=8.4.1; extra == 'test'
